[{"requestDate":"2022-01-01","requestType":"Служба \"Телефону довіри\"","gender":"Ж","requestCount":270,"violenceType":"психологічне, фізичне, економічне, сексуальне"},{"requestDate":"2022-01-01","requestType":"Служба \"Телефону довіри\"","gender":"Ч","requestCount":80,"violenceType":"психологічне, фізичне, економічне, сексуальне"},{"requestDate":"2022-04-01","requestType":"Служба \"Телефону довіри\"","gender":"Ж","requestCount":495,"violenceType":"психологічне, фізичне, економічне, сексуальне"},{"requestDate":"2022-04-01","requestType":"Служба \"Телефону довіри\"","gender":"Ч","requestCount":155,"violenceType":"психологічне, фізичне, економічне, сексуальне"},{"requestDate":"2022-07-01","requestType":"Служба \"Телефону довіри\"","gender":"Ж","requestCount":685,"violenceType":"психологічне, фізичне, економічне, сексуальне"},{"requestDate":"2022-07-01","requestType":"Служба \"Телефону довіри\"","gender":"Ч","requestCount":215,"violenceType":"психологічне, фізичне, економічне, сексуальне"},{"requestDate":"2022-10-01","requestType":"Служба \"Телефону довіри\"","gender":"Ж","requestCount":748,"violenceType":"психологічне, фізичне, економічне, сексуальне"},{"requestDate":"2022-10-01","requestType":"Служба \"Телефону довіри\"","gender":"Ч","requestCount":231,"violenceType":"психологічне, фізичне, економічне, сексуальне"},{"requestDate":"2023-01-01","requestType":"Служба \"Телефону довіри\"","gender":"Ж","requestCount":2767,"violenceType":"психологічне, фізичне, економічне, сексуальне"},{"requestDate":"2023-01-01","requestType":"Служба \"Телефону довіри\"","gender":"Ч","requestCount":598,"violenceType":"психологічне, фізичне, економічне, сексуальне"},{"requestDate":"2023-04-01","requestType":"Служба \"Телефону довіри\"","gender":"Ж","requestCount":2633,"violenceType":"психологічне, фізичне, економічне, сексуальне"},{"requestDate":"2023-04-01","requestType":"Служба \"Телефону довіри\"","gender":"Ч","requestCount":584,"violenceType":"психологічне, фізичне, економічне, сексуальне"},{"requestDate":"2023-07-01","requestType":"Служба \"Телефону довіри\"","gender":"Ж","requestCount":2770,"violenceType":"психологічне, фізичне, економічне, сексуальне"},{"requestDate":"2023-07-01","requestType":"Служба \"Телефону довіри\"","gender":"Ч","requestCount":641,"violenceType":"психологічне, фізичне, економічне, сексуальне"},{"requestDate":"2023-10-01","requestType":"Служба \"Телефону довіри\"","gender":"Ж","requestCount":1186,"violenceType":"психологічне, фізичне, економічне, сексуальне"},{"requestDate":"2023-10-01","requestType":"Служба \"Телефону довіри\"","gender":"Ч","requestCount":41,"violenceType":"психологічне, фізичне, економічне, сексуальне"},{"requestDate":"2024-01-01","requestType":"Служба \"Телефону довіри\"","gender":"Ж","requestCount":3537,"violenceType":"психологічне, фізичне, економічне, сексуальне"},{"requestDate":"2024-01-01","requestType":"Служба \"Телефону довіри\"","gender":"Ч","requestCount":569,"violenceType":"психологічне, фізичне, економічне, сексуальне"},{"requestDate":"2024-04-01","requestType":"Служба \"Телефону довіри\"","gender":"Ж","requestCount":3524,"violenceType":"психологічне, фізичне, економічне, сексуальне"},{"requestDate":"2024-04-01","requestType":"Служба \"Телефону довіри\"","gender":"Ч","requestCount":591,"violenceType":"психологічне, фізичне, економічне, сексуальне"},{"requestDate":"2024-07-01","requestType":"Служба \"Телефону довіри\"","gender":"Ж","requestCount":3599,"violenceType":"психологічне, фізичне, економічне, сексуальне"},{"requestDate":"2024-07-01","requestType":"Служба \"Телефону довіри\"","gender":"Ч","requestCount":636,"violenceType":"психологічне, фізичне, економічне, сексуальне"},{"requestDate":"2024-10-01","requestType":"Служба \"Телефону довіри\"","gender":"Ж","requestCount":3373,"violenceType":"психологічне, фізичне, економічне, сексуальне"},{"requestDate":"2024-10-01","requestType":"Служба \"Телефону довіри\"","gender":"Ч","requestCount":636,"violenceType":"психологічне, фізичне, економічне, сексуальне"},{"requestDate":"2025-01-01","requestType":"Служба \"Телефону довіри\"","gender":"Ж","requestCount":2580,"violenceType":"психологічне, фізичне, економічне, сексуальне"},{"requestDate":"2025-01-01","requestType":"Служба \"Телефону довіри\"","gender":"Ч","requestCount":636,"violenceType":"психологічне, фізичне, економічне, сексуальне"},{"requestDate":"2025-04-01","requestType":"Служба \"Телефону довіри\"","gender":"Ж","requestCount":1208,"violenceType":"психологічне, фізичне, економічне, сексуальне"},{"requestDate":"2025-04-01","requestType":"Служба \"Телефону довіри\"","gender":"Ч","requestCount":385,"violenceType":"психологічне, фізичне, економічне, сексуальне"},{"requestDate":"2025-07-01","requestType":"Служба \"Телефону довіри\"","gender":"Ж","requestCount":1197,"violenceType":"психологічне, фізичне, економічне, сексуальне"},{"requestDate":"2025-07-01","requestType":"Служба \"Телефону довіри\"","gender":"Ч","requestCount":427,"violenceType":"психологічне, фізичне, економічне, сексуальне"},{"requestDate":"2025-10-01","requestType":"Служба \"Телефону довіри\"","gender":"Ж","requestCount":1155,"violenceType":"психологічне, фізичне, економічне, сексуальне"},{"requestDate":"2025-10-01","requestType":"Служба \"Телефону довіри\"","gender":"Ч","requestCount":401,"violenceType":"психологічне, фізичне, економічне, сексуальне"},{"requestDate":"2026-01-01","requestType":"Служба \"Телефону довіри\"","gender":"Ж","requestCount":1248,"violenceType":"психологічне, фізичне, економічне, сексуальне"},{"requestDate":"2026-01-01","requestType":"Служба \"Телефону довіри\"","gender":"Ч","requestCount":303,"violenceType":"психологічне, фізичне, економічне, сексуальне"},{"requestDate":"2026-04-01","requestType":"Служба \"Телефону довіри\"","gender":"Ж","requestCount":1290,"violenceType":"психологічне, фізичне, економічне, сексуальне"},{"requestDate":"2026-04-01","requestType":"Служба \"Телефону довіри\"","gender":"Ч","requestCount":271,"violenceType":"психологічне, фізичне, економічне, сексуальне"},{"requestDate":"2022-01-01","requestType":"Денний центр","gender":"Ж","requestCount":0,"violenceType":"психологічне, фізичне, економічне, сексуальне"},{"requestDate":"2022-01-01","requestType":"Денний центр","gender":"Ч","requestCount":0,"violenceType":"психологічне, фізичне, економічне, сексуальне"},{"requestDate":"2022-04-01","requestType":"Денний центр","gender":"Ж","requestCount":0,"violenceType":"психологічне, фізичне, економічне, сексуальне"},{"requestDate":"2022-04-01","requestType":"Денний центр","gender":"Ч","requestCount":0,"violenceType":"психологічне, фізичне, економічне, сексуальне"},{"requestDate":"2022-07-01","requestType":"Денний центр","gender":"Ж","requestCount":0,"violenceType":"психологічне, фізичне, економічне, сексуальне"},{"requestDate":"2022-07-01","requestType":"Денний центр","gender":"Ч","requestCount":0,"violenceType":"психологічне, фізичне, економічне, сексуальне"},{"requestDate":"2022-10-01","requestType":"Денний центр","gender":"Ж","requestCount":1292,"violenceType":"психологічне, фізичне, економічне, сексуальне"},{"requestDate":"2022-10-01","requestType":"Денний центр","gender":"Ч","requestCount":97,"violenceType":"психологічне, фізичне, економічне, сексуальне"},{"requestDate":"2023-01-01","requestType":"Денний центр","gender":"Ж","requestCount":425,"violenceType":"психологічне, фізичне, економічне, сексуальне"},{"requestDate":"2023-01-01","requestType":"Денний центр","gender":"Ч","requestCount":47,"violenceType":"психологічне, фізичне, економічне, сексуальне"},{"requestDate":"2023-04-01","requestType":"Денний центр","gender":"Ж","requestCount":461,"violenceType":"психологічне, фізичне, економічне, сексуальне"},{"requestDate":"2023-04-01","requestType":"Денний центр","gender":"Ч","requestCount":27,"violenceType":"психологічне, фізичне, економічне, сексуальне"},{"requestDate":"2023-07-01","requestType":"Денний центр","gender":"Ж","requestCount":452,"violenceType":"психологічне, фізичне, економічне, сексуальне"},{"requestDate":"2023-07-01","requestType":"Денний центр","gender":"Ч","requestCount":60,"violenceType":"психологічне, фізичне, економічне, сексуальне"},{"requestDate":"2023-10-01","requestType":"Денний центр","gender":"Ж","requestCount":292,"violenceType":"психологічне, фізичне, економічне, сексуальне"},{"requestDate":"2023-10-01","requestType":"Денний центр","gender":"Ч","requestCount":22,"violenceType":"психологічне, фізичне, економічне, сексуальне"},{"requestDate":"2024-01-01","requestType":"Денний центр","gender":"Ж","requestCount":497,"violenceType":"психологічне, фізичне, економічне, сексуальне"},{"requestDate":"2024-01-01","requestType":"Денний центр","gender":"Ч","requestCount":71,"violenceType":"психологічне, фізичне, економічне, сексуальне"},{"requestDate":"2024-04-01","requestType":"Денний центр","gender":"Ж","requestCount":398,"violenceType":"психологічне, фізичне, економічне, сексуальне"},{"requestDate":"2024-04-01","requestType":"Денний центр","gender":"Ч","requestCount":25,"violenceType":"психологічне, фізичне, економічне, сексуальне"},{"requestDate":"2024-07-01","requestType":"Денний центр","gender":"Ж","requestCount":486,"violenceType":"психологічне, фізичне, економічне, сексуальне"},{"requestDate":"2024-07-01","requestType":"Денний центр","gender":"Ч","requestCount":75,"violenceType":"психологічне, фізичне, економічне, сексуальне"},{"requestDate":"2024-10-01","requestType":"Денний центр","gender":"Ж","requestCount":498,"violenceType":"психологічне, фізичне, економічне, сексуальне"},{"requestDate":"2024-10-01","requestType":"Денний центр","gender":"Ч","requestCount":80,"violenceType":"психологічне, фізичне, економічне, сексуальне"},{"requestDate":"2025-01-01","requestType":"Денний центр","gender":"Ж","requestCount":448,"violenceType":"психологічне, фізичне, економічне, сексуальне"},{"requestDate":"2025-01-01","requestType":"Денний центр","gender":"Ч","requestCount":69,"violenceType":"психологічне, фізичне, економічне, сексуальне"},{"requestDate":"2025-04-01","requestType":"Денний центр","gender":"Ж","requestCount":533,"violenceType":"психологічне, фізичне, економічне, сексуальне"},{"requestDate":"2025-04-01","requestType":"Денний центр","gender":"Ч","requestCount":69,"violenceType":"психологічне, фізичне, економічне, сексуальне"},{"requestDate":"2025-07-01","requestType":"Денний центр","gender":"Ж","requestCount":552,"violenceType":"психологічне, фізичне, економічне, сексуальне"},{"requestDate":"2025-07-01","requestType":"Денний центр","gender":"Ч","requestCount":148,"violenceType":"психологічне, фізичне, економічне, сексуальне"},{"requestDate":"2025-10-01","requestType":"Денний центр","gender":"Ж","requestCount":525,"violenceType":"психологічне, фізичне, економічне, сексуальне"},{"requestDate":"2025-10-01","requestType":"Денний центр","gender":"Ч","requestCount":163,"violenceType":"психологічне, фізичне, економічне, сексуальне"},{"requestDate":"2026-01-01","requestType":"Денний центр","gender":"Ж","requestCount":408,"violenceType":"психологічне, фізичне, економічне, сексуальне"},{"requestDate":"2026-01-01","requestType":"Денний центр","gender":"Ч","requestCount":45,"violenceType":"психологічне, фізичне, економічне, сексуальне"},{"requestDate":"2026-04-01","requestType":"Денний центр","gender":"Ж","requestCount":183,"violenceType":"психологічне, фізичне, економічне, сексуальне"},{"requestDate":"2026-04-01","requestType":"Денний центр","gender":"Ч","requestCount":28,"violenceType":"психологічне, фізичне, економічне, сексуальне"},{"requestDate":"2025-10-01","requestType":"Денний центр Стельмаха","gender":"Ж","requestCount":0,"violenceType":"психологічне, фізичне, економічне, сексуальне"},{"requestDate":"2025-10-01","requestType":"Денний центр Стельмаха","gender":"Ч","requestCount":0,"violenceType":"психологічне, фізичне, економічне, сексуальне"},{"requestDate":"2026-01-01","requestType":"Денний центр Стельмаха","gender":"Ж","requestCount":325,"violenceType":"психологічне, фізичне, економічне, сексуальне"},{"requestDate":"2026-01-01","requestType":"Денний центр Стельмаха","gender":"Ч","requestCount":29,"violenceType":"психологічне, фізичне, економічне, сексуальне"},{"requestDate":"2026-04-01","requestType":"Денний центр Стельмаха","gender":"Ж","requestCount":307,"violenceType":"психологічне, фізичне, економічне, сексуальне"},{"requestDate":"2026-04-01","requestType":"Денний центр Стельмаха","gender":"Ч","requestCount":51,"violenceType":"психологічне, фізичне, економічне, сексуальне"}]